bin/__init__.py
strongr/__init__.py
strongr/authdomain/__init__.py
strongr/authdomain/factory/__init__.py
strongr/authdomain/factory/queryfactory.py
strongr/authdomain/handler/__init__.py
strongr/authdomain/handler/isvaliduserhandler.py
strongr/authdomain/query/__init__.py
strongr/authdomain/query/isvaliduser.py
strongr/authdomain/service/__init__.py
strongr/authdomain/service/authservice.py
strongr/cli/__init__.py
strongr/cli/addclient.py
strongr/cli/cleanupcommand.py
strongr/cli/deploymanycommand.py
strongr/cli/deploysinglecommand.py
strongr/cli/destroymanycommand.py
strongr/cli/destroysinglecommand.py
strongr/cli/ensureminamountofnodescommand.py
strongr/cli/getfinishedjobscommand.py
strongr/cli/getjobstdout.py
strongr/cli/getsecret.py
strongr/cli/isvalidusercommand.py
strongr/cli/listdeployedvmscommand.py
strongr/cli/makedbcommand.py
strongr/cli/printconfig.py
strongr/cli/requestscheduledtasks.py
strongr/cli/runresourcemanager.py
strongr/cli/runrestservercommand.py
strongr/cli/runtestscommand.py
strongr/cli/runworkercommand.py
strongr/cli/testcommand.py
strongr/cli/wrapper/__init__.py
strongr/cli/wrapper/patchedcommand.py
strongr/clouddomain/__init__.py
strongr/clouddomain/command/__init__.py
strongr/clouddomain/command/deployvms.py
strongr/clouddomain/command/destroyvms.py
strongr/clouddomain/command/jobfinished.py
strongr/clouddomain/command/runjob.py
strongr/clouddomain/event/__init__.py
strongr/clouddomain/event/inter/__init__.py
strongr/clouddomain/event/inter/jobfinished.py
strongr/clouddomain/event/inter/vmcreated.py
strongr/clouddomain/event/inter/vmdestroyed.py
strongr/clouddomain/event/inter/vmnew.py
strongr/clouddomain/event/inter/vmready.py
strongr/clouddomain/event/intra/__init__.py
strongr/clouddomain/event/intra/saltjobfinished.py
strongr/clouddomain/exception/__init__.py
strongr/clouddomain/factory/__init__.py
strongr/clouddomain/factory/commandfactory.py
strongr/clouddomain/factory/interdomaineventfactory.py
strongr-1.2.dist-info/LICENSE
strongr-1.2.dist-info/METADATA
strongr-1.2.dist-info/WHEEL
strongr-1.2.dist-info/top_level.txt
strongr-1.2.dist-info/RECORD
